flag.py
flag_leak_R-0.1.0.dist-info/LICENSE
flag_leak_R-0.1.0.dist-info/METADATA
flag_leak_R-0.1.0.dist-info/WHEEL
flag_leak_R-0.1.0.dist-info/top_level.txt
flag_leak_R-0.1.0.dist-info/RECORD
