Metadata-Version: 2.1
Name: flag_leak_R
Version: 0.1.0
Summary: Leaking environment variables via HTTP requests
Author: Your Name
Author-email: your_email@example.com
Classifier: Programming Language :: Python :: 3
Classifier: License :: OSI Approved :: MIT License
Classifier: Operating System :: OS Independent
Requires-Python: >=3.6
License-File: LICENSE
Requires-Dist: requests
